README.rst
setup.py
dbconfigurator/__init__.py
dbconfigurator/get_db.py
dbconfigurator/register_config.py
dbconfigurator.egg-info/PKG-INFO
dbconfigurator.egg-info/SOURCES.txt
dbconfigurator.egg-info/dependency_links.txt
dbconfigurator.egg-info/requires.txt
dbconfigurator.egg-info/top_level.txt
dbconfigurator/config/__init__.py
dbconfigurator/config/get_db.py