Metadata-Version: 1.1
Name: dbconfigurator
Version: 0.1.4
Summary: Pip installable SQLAlchemy-style config
Home-page: https://github.com/artemishealth/prometheus/tree/master/rv816/GapsInCare/Pycode/Scripts/Modules/dbconfig
Author: Ryan Vass
Author-email: rvsax16@gmail.com
License: UNKNOWN
Platform: UNKNOWN
Classifier: Development Status :: 2 - Pre-Alpha
Classifier: Programming Language :: Python
Classifier: Programming Language :: Python :: 2
Classifier: Programming Language :: Python :: 2.7
Classifier: Programming Language :: Python :: 3
Classifier: Programming Language :: Python :: 3.4
Classifier: Programming Language :: Python :: 3.5
